{
  "navbar": {
    "sign_in": "Eintragen",
    "create_account": "Konto erstellen",
    "logout": "Abmelden"
  },

  "footer": {
    "information": "Information",
    "privacy_policy": "Datenschutzbestimmungen",
    "terms_conditions": "Bedingungen und Konditionen",
    "contact": "Kontakt",

    "customer_service": "Kundenbetreuung",
    "delivery_payments": "Lieferung und Zahlungen",
    "returns_refunds": "Rückgabe und Rückerstattung",

    "helpful_links": "Hilfreiche Links",
    "faq": "FAQs"
  },

  "order_completed": {
    "order_completed": "Auftrag abgeschlossen",
    "order_completed_description": "Ihre Bestellung wurde abgeschlossen",
    "payment_processing": "Warten auf die Bearbeitung der Zahlung"
  }
}